<?xml version="1.0" encoding="utf-8"?>
<SL_Item xmlns:xsi="http://www.w3.org/2001/XMLSchema-instance" xmlns:xsd="http://www.w3.org/2001/XMLSchema">
  <OnlyChangeVisuals>false</OnlyChangeVisuals>
  <ReplaceEffects>false</ReplaceEffects>
  <Target_ItemID>8000050</Target_ItemID>
  <New_ItemID>8999050</New_ItemID>
  <Name>Activated Plague Aura</Name>
  <Description />
  <LegacyItemID>-1</LegacyItemID>
  <IsPickable>false</IsPickable>
  <IsUsable>false</IsUsable>
  <QtyRemovedOnUse>1</QtyRemovedOnUse>
  <GroupItemInDisplay>false</GroupItemInDisplay>
  <HasPhysicsWhenWorld>false</HasPhysicsWhenWorld>
  <RepairedInRest>true</RepairedInRest>
  <BehaviorOnNoDurability>NotSet</BehaviorOnNoDurability>
  <CastLocomotionEnabled>false</CastLocomotionEnabled>
  <MobileCastMovementMult>-1</MobileCastMovementMult>
  <CastModifier>Immobilized</CastModifier>
  <CastSheatheRequired>1</CastSheatheRequired>
  <Tags />
  <EffectTransforms />
</SL_Item>